{
    "profession": "animal_tamer",
    "removeOtherTrades": false,
    "trades": [
      {
        "offer": {
          "itemKey": "alexsmobs:flying_fish_bucket",
          "amount": 1
        },
        "request": {
            "itemKey": "alexsmobs:flying_fish",
            "amount": 1
          },
        "additionalRequest": {
            "itemKey": "minecraft:bucket",
            "amount": 1
        },
        "tradeExp": 10,
        "maxUses": 5,
        "priceMultiplier": 0.08,
        "tradeLevel": 3
      },
      {
        "offer": {
          "itemKey": "alexsmobs:blobfish_bucket",
          "amount": 1
        },
        "request": {
            "itemKey": "alexsmobs:blobfish",
            "amount": 1
          },
        "additionalRequest": {
            "itemKey": "minecraft:bucket",
            "amount": 1
        },
        "tradeExp": 10,
        "maxUses": 5,
        "priceMultiplier": 0.08,
        "tradeLevel": 3
      },
      {
        "offer": {
          "itemKey": "alexsmobs:cosmic_cod_bucket",
          "amount": 1
        },
        "request": {
            "itemKey": "alexsmobs:cosmic_cod",
            "amount": 1
          },
        "additionalRequest": {
            "itemKey": "minecraft:bucket",
            "amount": 1
        },
        "tradeExp": 10,
        "maxUses": 5,
        "priceMultiplier": 0.08,
        "tradeLevel": 4
      }
    ]
  }